MANIFEST.in
README.md
setup.py
td4a-server
td4a/__init__.py
td4a.egg-info/PKG-INFO
td4a.egg-info/SOURCES.txt
td4a.egg-info/dependency_links.txt
td4a.egg-info/not-zip-safe
td4a.egg-info/requires.txt
td4a.egg-info/top_level.txt
td4a/controllers/__init__.py
td4a/controllers/config.py
td4a/controllers/hosts.py
td4a/controllers/inventory.py
td4a/controllers/link.py
td4a/controllers/render.py
td4a/controllers/retrieve.py
td4a/controllers/schema.py
td4a/controllers/validate.py
td4a/models/__init__.py
td4a/models/exception_handler.py
td4a/models/filters.py
td4a/models/inventory.py
td4a/models/sort_commented_map.py
td4a/models/td4ayaml.py
td4a/static/data.yml
td4a/static/favicon.ico
td4a/static/index.html
td4a/static/template.j2
td4a/static/css/angular-material.css
td4a/static/css/app.css
td4a/static/css/codemirror.css
td4a/static/css/dialog.css
td4a/static/css/material.css
td4a/static/js/app.js
td4a/static/js/main.min.js