Metadata-Version: 1.0
Name: td4a
Version: 2.0.3
Summary: A browser based jinja template renderer
Home-page: http://github.com/cidrblock/td4a
Author: Bradley A. Thornton
Author-email: brad@thethorntons.net
License: MIT
Platform: UNKNOWN
